Workbook

Sheet Parametros
A1: MOOVY - Parametros de Proyeccion
A2: Modifica los valores en AZUL para cambiar las proyecciones
A4: PARAMETROS GENERALES
B5: Conservador | C5: Moderado | D5: Optimista | E5: Notas
A6: Ticket promedio pedido ($) | B6: 15000 | C6: 20000 | D6: 25000 | E6: Monto promedio que gasta un comprador
A7: Pedidos/dia MES 1 | B7: 15 | C7: 25 | D7: 40 | E7: Primeros 30 dias de lanzamiento
A8: Pedidos/dia MES 2 | B8: 30 | C8: 50 | D8: 80 | E8: Comision 8% activa
A9: Pedidos/dia MES 3 | B9: 45 | C9: 70 | D9: 110 | E9: Crecimiento orgánico
A10: Pedidos/dia MES 4 | B10: 55 | C10: 85 | D10: 130 | E10: Network effect
A11: Pedidos/dia MES 5 | B11: 65 | C11: 100 | D11: 150 | E11: Estabilización
A12: Pedidos/dia MES 6 | B12: 75 | C12: 120 | D12: 170 | E12: Madurez inicial
A13: Comercios activos MES 1 | B13: 5 | C13: 8 | D13: 12 | E13: Lanzamiento
A14: Comercios activos MES 2 | B14: 8 | C14: 15 | D14: 22 | E14: Boca en boca
A15: Comercios activos MES 3 | B15: 12 | C15: 22 | D15: 32
A16: Comercios activos MES 4 | B16: 16 | C16: 28 | D16: 40
A17: Comercios activos MES 5 | B17: 20 | C17: 35 | D17: 48
A18: Comercios activos MES 6 | B18: 25 | C18: 42 | D18: 55
A19: % pedidos Marketplace (del total) | B19: 0.15 | C19: 0.2 | D19: 0.25 | E19: Marketplace activo desde dia 1
A20: Distancia promedio entrega (km) | B20: 3 | C20: 3 | D20: 3 | E20: Zona A Ushuaia
A21: % pedidos en moto | B21: 0.7 | C21: 0.7 | D21: 0.7 | E21: Principal vehiculo delivery
A22: % pedidos en auto | B22: 0.2 | C22: 0.2 | D22: 0.2 | E22: Paquetes medianos
A23: % pedidos en bici | B23: 0.1 | C23: 0.1 | D23: 0.1 | E23: Cercanos
A25: COSTOS Y COMISIONES (Biblia v4)
B26: Valor | E26: Notas
A27: Comision comercios MES 1 | B27: 0 | E27: 0% primer mes
A28: Comision comercios MES 2+ | B28: 0.08 | E28: 8% sobre ventas
A29: Comision marketplace | B29: 0.12 | E29: 12% desde dia 1
A30: Costo operativo embebido | B30: 0.05 | E30: 5% del subtotal en delivery
A31: Costo MercadoPago | B31: 0.04 | E31: ~3.81% redondeado a 4%
A32: % pedidos con MercadoPago | B32: 0.5 | E32: Estimado 50/50 cash vs MP
A33: Fee repartidor (% del viaje) | B33: 0.8 | E33: 80% para el driver
A34: Fee minimo moto ($) | B34: 1500 | E34: Biblia v4
A35: Fee minimo auto ($) | B35: 3000 | E35: Biblia v4 actualizado
A36: Fee minimo bici ($) | B36: 800 | E36: Biblia v4
A37: Costo/km moto ($) | B37: 76 | E37: Biblia v4 - $1,655/L
A38: Factor distancia | B38: 2.2 | E38: Ida + vuelta + maniobras
... A42: % comercios que pagan publicidad | B42: 0.3 | E42: No todos pagan

Sheet Conservador
A1: MOOVY - Proyeccion 6 Meses: CONSERVADOR
A2: Todos los montos en pesos argentinos (ARS). Los valores se recalculan desde la hoja Parametros.
B4: Mes 1 | C4: Mes 2 | D4: Mes 3 | E4: Mes 4 | F4: Mes 5 | G4: Mes 6 | H4: TOTAL
A6: VOLUMEN DE OPERACION
A7: Pedidos por dia | B7: =Parametros!B7 -> 15 | C7: =Parametros!B8 -> 30 | D7: =Parametros!B9 -> 45 | E7: =Parametros!B10 -> 55 | F7: =Parametros!B11 -> 65 | G7: =Parametros!B12 -> 75 | H7: =AVERAGE(B7:G7) -> 47.5
A8: Pedidos por mes | B8: =B7*30 -> 450 | C8: =C7*30 -> 900 | D8: =D7*30 -> 1350 | E8: =E7*30 -> 1650 | F8: =F7*30 -> 1950 | G8: =G7*30 -> 2250 | H8: =SUM(B8:G8) -> 8550
A9: Comercios activos | B9: =Parametros!B13 -> 5 | C9: =Parametros!B14 -> 8 | D9: =Parametros!B15 -> 12 | E9: =Parametros!B16 -> 16 | F9: =Parametros!B17 -> 20 | G9: =Parametros!B18 -> 25 | H9: =MAX(B9:G9) -> 25
A10: Ticket promedio ($) | B10: =Parametros!B6 -> 15000 | C10: =Parametros!B6 -> 15000 | D10: =Parametros!B6 -> 15000 | E10: =Parametros!B6 -> 15000 | F10: =Parametros!B6 -> 15000 | G10: =Parametros!B6 -> 15000
A11: GMV mensual ($) | B11: =B8*B10 -> 6750000 | C11: =C8*C10 -> 13500000 | D11: =D8*D10 -> 20250000 | E11: =E8*E10 -> 24750000 | F11: =F8*F10 -> 29250000 | G11: =G8*G10 -> 33750000 | H11: =SUM(B11:G11) -> 128250000
A13: INGRESOS
A14: Comision comercios gastro ($) | B14: =B11*(1-Parametros!B19)*Parametros!B27 -> 0 | C14: =C11*(1-Parametros!B19)*Parametros!B28 -> 918000 | D14: =D11*(1-Parametros!B19)*Parametros!B28 -> 1377000 | E14: =E11*(1-Parametros!B19)*Parametros!B28 -> 1683000 | F14: =F11*(1-Parametros!B19)*Parametros!B28 -> 1989000 | G14: =G11*(1-Parametros!B19)*Parametros!B28 -> 2295000 | H14: =SUM(B14:G14) -> 8262000
A15: Comision marketplace ($) | B15: =B11*Parametros!B19*Parametros!B29 -> 121500 | C15: =C11*Parametros!B19*Parametros!B29 -> 243000 | D15: =D11*Parametros!B19*Parametros!B29 -> 364500 | E15: =E11*Parametros!B19*Parametros!B29 -> 445500 | F15: =F11*Parametros!B19*Parametros!B29 -> 526500 | G15: =G11*Parametros!B19*Parametros!B29 -> 607500 | H15: =SUM(B15:G15) -> 2308500
A16: Ingresos delivery (20% del fee) | B16: =B8*(Parametros!B21*Parametros!B34+Parametros!B22*Parametros!B35+Parametros!B23*Parametros!B36)*(1-Parametros!B33) -> 155700 | C16: =C8*(Parametros!B21*Parametros!B34+Parametros!B22*Parametros!B35+Parametros!B23*Parametros!B36)*(1-Parametros!B33) -> 311400 | D16: =D8*(Parametros!B21*Parametros!B34+Parametros!B22*Parametros!B35+Parametros!B23*Parametros!B36)*(1-Parametros!B33) -> 467100 | E16: =E8*(Parametros!B21*Parametros!B34+Parametros!B22*Parametros!B35+Parametros!B23*Parametros!B36)*(1-Parametros!B33) -> 570900 | F16: =F8*(Parametros!B21*Parametros!B34+Parametros!B22*Parametros!B35+Parametros!B23*Parametros!B36)*(1-Parametros!B33) -> 674700 | G16: =G8*(Parametros!B21*Parametros!B34+Parametros!B22*Parametros!B35+Parametros!B23*Parametros!B36)*(1-Parametros!B33) -> 778500 | H16: =SUM(B16:G16) -> 2958300
A17: Ingreso operativo 5% embebido ($) | B17: =B11*Parametros!B30 -> 337500 | C17: =C11*Parametros!B30 -> 675000 | D17: =D11*Parametros!B30 -> 1012500 | E17: =E11*Parametros!B30 -> 1237500 | F17: =F11*Parametros!B30 -> 1462500 | G17: =G11*Parametros!B30 -> 1687500 | H17: =SUM(B17:G17) -> 6412500
A18: Ingresos publicidad comercios ($) | B18: =B9*Parametros!B41*Parametros!B42 -> 75000 | C18: =C9*Parametros!B41*Parametros!B42 -> 120000 | D18: =D9*Parametros!B41*Parametros!B42 -> 180000 | E18: =E9*Parametros!B41*Parametros!B42 -> 240000 | F18: =F9*Parametros!B41*Parametros!B42 -> 300000 | G18: =G9*Parametros!B41*Parametros!B42 -> 375000 | H18: =SUM(B18:G18) -> 1290000
A19: TOTAL INGRESOS BRUTOS ($) | B19: =SUM(B14:B18) -> 689700 | C19: =SUM(C14:C18) -> 2267400 | D19: =SUM(D14:D18) -> 3401100 | E19: =SUM(E14:E18) -> 4176900 | F19: =SUM(F14:F18) -> 4952700 | G19: =SUM(G14:G18) -> 5743500 | H19: =SUM(B19:G19) -> 21231300
A21: EGRESOS
A22: Costo MercadoPago ($) | B22: =B11*Parametros!B32*Parametros!B31 -> 135000 | C22: =C11*Parametros!B32*Parametros!B31 -> 270000 | D22: =D11*Parametros!B32*Parametros!B31 -> 405000 | E22: =E11*Parametros!B32*Parametros!B31 -> 495000 | F22: =F11*Parametros!B32*Parametros!B31 -> 585000 | G22: =G11*Parametros!B32*Parametros!B31 -> 675000 | H22: =SUM(B22:G22) -> 2565000
A23: Gastos fijos mensuales ($) | B23: =Parametros!B39 -> 440641 | C23: =Parametros!B39 -> 440641 | D23: =Parametros!B39 -> 440641 | E23: =Parametros!B39 -> 440641 | F23: =Parametros!B39 -> 440641 | G23: =Parametros!B39 -> 440641 | H23: =SUM(B23:G23) -> 2643846
A24: Cashback MOOVER estimado ($) | B24: =B11*0.01 -> 67500 | C24: =C11*0.01 -> 135000 | D24: =D11*0.01 -> 202500 | E24: =E11*0.01 -> 247500 | F24: =F11*0.01 -> 292500 | G24: =G11*0.01 -> 337500 | H24: =SUM(B24:G24) -> 1282500
A25: Reembolsos y cancelaciones ($) | B25: =B11*0.02 -> 135000 | C25: =C11*0.02 -> 270000 | D25: =D11*0.02 -> 405000 | E25: =E11*0.02 -> 495000 | F25: =F11*0.02 -> 585000 | G25: =G11*0.02 -> 675000 | H25: =SUM(B25:G25) -> 2565000
A26: TOTAL EGRESOS ($) | B26: =SUM(B22:B25) -> 778141 | C26: =SUM(C22:C25) -> 1115641 | D26: =SUM(D22:D25) -> 1453141 | E26: =SUM(E22:E25) -> 1678141 | F26: =SUM(F22:F25) -> 1903141 | G26: =SUM(G22:G25) -> 2128141 | H26: =SUM(B26:G26) -> 9056346
A28: RESULTADO
A29: RESULTADO NETO MENSUAL ($) | B29: =B19-B26 -> -88441 | C29: =C19-C26 -> 1151759 | D29: =D19-D26 -> 1947959 | E29: =E19-E26 -> 2498759 | F29: =F19-F26 -> 3049559 | G29: =G19-G26 -> 3615359 | H29: =SUM(B29:G29) -> 12174954
A30: Retiro fundador (10% si neto > 0) | B30: =IF(B29>0,B29*Parametros!B40,0) -> 0 | C30: =IF(C29>0,C29*Parametros!B40,0) -> 115175.9 | D30: =IF(D29>0,D29*Parametros!B40,0) -> 194795.9 | E30: =IF(E29>0,E29*Parametros!B40,0) -> 249875.9 | F30: =IF(F29>0,F29*Parametros!B40,0) -> 304955.9 | G30: =IF(G29>0,G29*Parametros!B40,0) -> 361535.9 | H30: =SUM(B30:G30) -> 1226339.5
A31: QUEDA EN CAJA ($) | B31: =B29-B30 -> -88441 | C31: =C29-C30 -> 1036583.1 | D31: =D29-D30 -> 1753163.1 | E31: =E29-E30 -> 2248883.1 | F31: =F29-F30 -> 2744603.1 | G31: =G29-G30 -> 3253823.1 | H31: =SUM(B31:G31) -> 10948614
A32: CAJA ACUMULADA ($) | B32: =B31 -> -88441 | C32: =B32+C31 -> 948142.1 | D32: =C32+D31 -> 2701305.2 | E32: =D32+E31 -> 4950188.3 | F32: =E32+F31 -> 7694791.4 | G32: =F32+G31 -> 10948614
A34: METRICAS CLAVE
A35: Margen neto (%) | B35: =IF(B19=0,0,B29/B19) -> -0.12823111 | C35: =IF(C19=0,0,C29/C19) -> 0.50796463 | D35: =IF(D19=0,0,D29/D19) -> 0.57274382 | E35: =IF(E19=0,0,E29/E19) -> 0.5982329 | F35: =IF(F19=0,0,F29/F19) -> 0.61573667 | G35: =IF(G19=0,0,G29/G19) -> 0.62946966
A36: Ingreso por pedido ($) | B36: =IF(B8=0,0,B19/B8) -> 1532.6667 | C36: =IF(C8=0,0,C19/C8) -> 2519.3333 | D36: =IF(D8=0,0,D19/D8) -> 2519.3333 | E36: =IF(E8=0,0,E19/E8) -> 2531.4545 | F36: =IF(F8=0,0,F19/F8) -> 2539.8462 | G36: =IF(G8=0,0,G19/G8) -> 2552.6667
A37: GMV diario ($) | B37: =B11/30 -> 225000 | C37: =C11/30 -> 450000 | D37: =D11/30 -> 675000 | E37: =E11/30 -> 825000 | F37: =F11/30 -> 975000 | G37: =G11/30 -> 1125000

Sheet Moderado
A1: MOOVY - Proyeccion 6 Meses: MODERADO
A2: Todos los montos en pesos argentinos (ARS). Los valores se recalculan desde la hoja Parametros.
B4: Mes 1 | C4: Mes 2 | D4: Mes 3 | E4: Mes 4 | F4: Mes 5 | G4: Mes 6 | H4: TOTAL
A6: VOLUMEN DE OPERACION
A7: Pedidos por dia | B7: =Parametros!C7 -> 25 | C7: =Parametros!C8 -> 50 | D7: =Parametros!C9 -> 70 | E7: =Parametros!C10 -> 85 | F7: =Parametros!C11 -> 100 | G7: =Parametros!C12 -> 120 | H7: =AVERAGE(B7:G7) -> 75
A8: Pedidos por mes | B8: =B7*30 -> 750 | C8: =C7*30 -> 1500 | D8: =D7*30 -> 2100 | E8: =E7*30 -> 2550 | F8: =F7*30 -> 3000 | G8: =G7*30 -> 3600 | H8: =SUM(B8:G8) -> 13500
A9: Comercios activos | B9: =Parametros!C13 -> 8 | C9: =Parametros!C14 -> 15 | D9: =Parametros!C15 -> 22 | E9: =Parametros!C16 -> 28 | F9: =Parametros!C17 -> 35 | G9: =Parametros!C18 -> 42 | H9: =MAX(B9:G9) -> 42
A10: Ticket promedio ($) | B10: =Parametros!C6 -> 20000 | C10: =Parametros!C6 -> 20000 | D10: =Parametros!C6 -> 20000 | E10: =Parametros!C6 -> 20000 | F10: =Parametros!C6 -> 20000 | G10: =Parametros!C6 -> 20000
A11: GMV mensual ($) | B11: =B8*B10 -> 15000000 | C11: =C8*C10 -> 30000000 | D11: =D8*D10 -> 42000000 | E11: =E8*E10 -> 51000000 | F11: =F8*F10 -> 60000000 | G11: =G8*G10 -> 72000000 | H11: =SUM(B11:G11) -> 270000000
A13: INGRESOS
A14: Comision comercios gastro ($) | B14: =B11*(1-Parametros!C19)*Parametros!B27 -> 0 | C14: =C11*(1-Parametros!C19)*Parametros!B28 -> 1920000 | D14: =D11*(1-Parametros!C19)*Parametros!B28 -> 2688000 | E14: =E11*(1-Parametros!C19)*Parametros!B28 -> 3264000 | F14: =F11*(1-Parametros!C19)*Parametros!B28 -> 3840000 | G14: =G11*(1-Parametros!C19)*Parametros!B28 -> 4608000 | H14: =SUM(B14:G14) -> 16320000
A15: Comision marketplace ($) | B15: =B11*Parametros!C19*Parametros!B29 -> 360000 | C15: =C11*Parametros!C19*Parametros!B29 -> 720000 | D15: =D11*Parametros!C19*Parametros!B29 -> 1008000 | E15: =E11*Parametros!C19*Parametros!B29 -> 1224000 | F15: =F11*Parametros!C19*Parametros!B29 -> 1440000 | G15: =G11*Parametros!C19*Parametros!B29 -> 1728000 | H15: =SUM(B15:G15) -> 6480000
A16: Ingresos delivery (20% del fee) | B16: =B8*(Parametros!C21*Parametros!B34+Parametros!C22*Parametros!B35+Parametros!C23*Parametros!B36)*(1-Parametros!B33) -> 259500 | C16: =C8*(Parametros!C21*Parametros!B34+Parametros!C22*Parametros!B35+Parametros!C23*Parametros!B36)*(1-Parametros!B33) -> 519000 | D16: =D8*(Parametros!C21*Parametros!B34+Parametros!C22*Parametros!B35+Parametros!C23*Parametros!B36)*(1-Parametros!B33) -> 726600 | E16: =E8*(Parametros!C21*Parametros!B34+Parametros!C22*Parametros!B35+Parametros!C23*Parametros!B36)*(1-Parametros!B33) -> 882300 | F16: =F8*(Parametros!C21*Parametros!B34+Parametros!C22*Parametros!B35+Parametros!C23*Parametros!B36)*(1-Parametros!B33) -> 1038000 | G16: =G8*(Parametros!C21*Parametros!B34+Parametros!C22*Parametros!B35+Parametros!C23*Parametros!B36)*(1-Parametros!B33) -> 1245600 | H16: =SUM(B16:G16) -> 4671000
A17: Ingreso operativo 5% embebido ($) | B17: =B11*Parametros!B30 -> 750000 | C17: =C11*Parametros!B30 -> 1500000 | D17: =D11*Parametros!B30 -> 2100000 | E17: =E11*Parametros!B30 -> 2550000 | F17: =F11*Parametros!B30 -> 3000000 | G17: =G11*Parametros!B30 -> 3600000 | H17: =SUM(B17:G17) -> 13500000
A18: Ingresos publicidad comercios ($) | B18: =B9*Parametros!B41*Parametros!B42 -> 120000 | C18: =C9*Parametros!B41*Parametros!B42 -> 225000 | D18: =D9*Parametros!B41*Parametros!B42 -> 330000 | E18: =E9*Parametros!B41*Parametros!B42 -> 420000 | F18: =F9*Parametros!B41*Parametros!B42 -> 525000 | G18: =G9*Parametros!B41*Parametros!B42 -> 630000 | H18: =SUM(B18:G18) -> 2250000
A19: TOTAL INGRESOS BRUTOS ($) | B19: =SUM(B14:B18) -> 1489500 | C19: =SUM(C14:C18) -> 4884000 | D19: =SUM(D14:D18) -> 6852600 | E19: =SUM(E14:E18) -> 8340300 | F19: =SUM(F14:F18) -> 9843000 | G19: =SUM(G14:G18) -> 11811600 | H19: =SUM(B19:G19) -> 43221000
A21: EGRESOS
A22: Costo MercadoPago ($) | B22: =B11*Parametros!B32*Parametros!B31 -> 300000 | C22: =C11*Parametros!B32*Parametros!B31 -> 600000 | D22: =D11*Parametros!B32*Parametros!B31 -> 840000 | E22: =E11*Parametros!B32*Parametros!B31 -> 1020000 | F22: =F11*Parametros!B32*Parametros!B31 -> 1200000 | G22: =G11*Parametros!B32*Parametros!B31 -> 1440000 | H22: =SUM(B22:G22) -> 5400000
A23: Gastos fijos mensuales ($) | B23: =Parametros!B39 -> 440641 | C23: =Parametros!B39 -> 440641 | D23: =Parametros!B39 -> 440641 | E23: =Parametros!B39 -> 440641 | F23: =Parametros!B39 -> 440641 | G23: =Parametros!B39 -> 440641 | H23: =SUM(B23:G23) -> 2643846
A24: Cashback MOOVER estimado ($) | B24: =B11*0.01 -> 150000 | C24: =C11*0.01 -> 300000 | D24: =D11*0.01 -> 420000 | E24: =E11*0.01 -> 510000 | F24: =F11*0.01 -> 600000 | G24: =G11*0.01 -> 720000 | H24: =SUM(B24:G24) -> 2700000
A25: Reembolsos y cancelaciones ($) | B25: =B11*0.02 -> 300000 | C25: =C11*0.02 -> 600000 | D25: =D11*0.02 -> 840000 | E25: =E11*0.02 -> 1020000 | F25: =F11*0.02 -> 1200000 | G25: =G11*0.02 -> 1440000 | H25: =SUM(B25:G25) -> 5400000
A26: TOTAL EGRESOS ($) | B26: =SUM(B22:B25) -> 1190641 | C26: =SUM(C22:C25) -> 1940641 | D26: =SUM(D22:D25) -> 2540641 | E26: =SUM(E22:E25) -> 2990641 | F26: =SUM(F22:F25) -> 3440641 | G26: =SUM(G22:G25) -> 4040641 | H26: =SUM(B26:G26) -> 16143846
A28: RESULTADO
A29: RESULTADO NETO MENSUAL ($) | B29: =B19-B26 -> 298859 | C29: =C19-C26 -> 2943359 | D29: =D19-D26 -> 4311959 | E29: =E19-E26 -> 5349659 | F29: =F19-F26 -> 6402359 | G29: =G19-G26 -> 7770959 | H29: =SUM(B29:G29) -> 27077154
A30: Retiro fundador (10% si neto > 0) | B30: =IF(B29>0,B29*Parametros!B40,0) -> 29885.9 | C30: =IF(C29>0,C29*Parametros!B40,0) -> 294335.9 | D30: =IF(D29>0,D29*Parametros!B40,0) -> 431195.9 | E30: =IF(E29>0,E29*Parametros!B40,0) -> 534965.9 | F30: =IF(F29>0,F29*Parametros!B40,0) -> 640235.9 | G30: =IF(G29>0,G29*Parametros!B40,0) -> 777095.9 | H30: =SUM(B30:G30) -> 2707715.4
A31: QUEDA EN CAJA ($) | B31: =B29-B30 -> 268973.1 | C31: =C29-C30 -> 2649023.1 | D31: =D29-D30 -> 3880763.1 | E31: =E29-E30 -> 4814693.1 | F31: =F29-F30 -> 5762123.1 | G31: =G29-G30 -> 6993863.1 | H31: =SUM(B31:G31) -> 24369439
A32: CAJA ACUMULADA ($) | B32: =B31 -> 268973.1 | C32: =B32+C31 -> 2917996.2 | D32: =C32+D31 -> 6798759.3 | E32: =D32+E31 -> 11613452 | F32: =E32+F31 -> 17375576 | G32: =F32+G31 -> 24369439
A34: METRICAS CLAVE
A35: Margen neto (%) | B35: =IF(B19=0,0,B29/B19) -> 0.20064384 | C35: =IF(C19=0,0,C29/C19) -> 0.60265336 | D35: =IF(D19=0,0,D29/D19) -> 0.62924423 | E35: =IF(E19=0,0,E29/E19) -> 0.64142285 | F35: =IF(F19=0,0,F29/F19) -> 0.65044793 | G35: =IF(G19=0,0,G29/G19) -> 0.65790909
A36: Ingreso por pedido ($) | B36: =IF(B8=0,0,B19/B8) -> 1986 | C36: =IF(C8=0,0,C19/C8) -> 3256 | D36: =IF(D8=0,0,D19/D8) -> 3263.1429 | E36: =IF(E8=0,0,E19/E8) -> 3270.7059 | F36: =IF(F8=0,0,F19/F8) -> 3281 | G36: =IF(G8=0,0,G19/G8) -> 3281
A37: GMV diario ($) | B37: =B11/30 -> 500000 | C37: =C11/30 -> 1000000 | D37: =D11/30 -> 1400000 | E37: =E11/30 -> 1700000 | F37: =F11/30 -> 2000000 | G37: =G11/30 -> 2400000

Sheet Optimista
A1: MOOVY - Proyeccion 6 Meses: OPTIMISTA
A2: Todos los montos en pesos argentinos (ARS). Los valores se recalculan desde la hoja Parametros.
B4: Mes 1 | C4: Mes 2 | D4: Mes 3 | E4: Mes 4 | F4: Mes 5 | G4: Mes 6 | H4: TOTAL
A6: VOLUMEN DE OPERACION
A7: Pedidos por dia | B7: =Parametros!D7 -> 40 | C7: =Parametros!D8 -> 80 | D7: =Parametros!D9 -> 110 | E7: =Parametros!D10 -> 130 | F7: =Parametros!D11 -> 150 | G7: =Parametros!D12 -> 170 | H7: =AVERAGE(B7:G7) -> 113.33333
A8: Pedidos por mes | B8: =B7*30 -> 1200 | C8: =C7*30 -> 2400 | D8: =D7*30 -> 3300 | E8: =E7*30 -> 3900 | F8: =F7*30 -> 4500 | G8: =G7*30 -> 5100 | H8: =SUM(B8:G8) -> 20400
A9: Comercios activos | B9: =Parametros!D13 -> 12 | C9: =Parametros!D14 -> 22 | D9: =Parametros!D15 -> 32 | E9: =Parametros!D16 -> 40 | F9: =Parametros!D17 -> 48 | G9: =Parametros!D18 -> 55 | H9: =MAX(B9:G9) -> 55
A10: Ticket promedio ($) | B10: =Parametros!D6 -> 25000 | C10: =Parametros!D6 -> 25000 | D10: =Parametros!D6 -> 25000 | E10: =Parametros!D6 -> 25000 | F10: =Parametros!D6 -> 25000 | G10: =Parametros!D6 -> 25000
A11: GMV mensual ($) | B11: =B8*B10 -> 30000000 | C11: =C8*C10 -> 60000000 | D11: =D8*D10 -> 82500000 | E11: =E8*E10 -> 97500000 | F11: =F8*F10 -> 112500000 | G11: =G8*G10 -> 127500000 | H11: =SUM(B11:G11) -> 510000000
A13: INGRESOS
A14: Comision comercios gastro ($) | B14: =B11*(1-Parametros!D19)*Parametros!B27 -> 0 | C14: =C11*(1-Parametros!D19)*Parametros!B28 -> 3600000 | D14: =D11*(1-Parametros!D19)*Parametros!B28 -> 4950000 | E14: =E11*(1-Parametros!D19)*Parametros!B28 -> 5850000 | F14: =F11*(1-Parametros!D19)*Parametros!B28 -> 6750000 | G14: =G11*(1-Parametros!D19)*Parametros!B28 -> 7650000 | H14: =SUM(B14:G14) -> 28800000
A15: Comision marketplace ($) | B15: =B11*Parametros!D19*Parametros!B29 -> 900000 | C15: =C11*Parametros!D19*Parametros!B29 -> 1800000 | D15: =D11*Parametros!D19*Parametros!B29 -> 2475000 | E15: =E11*Parametros!D19*Parametros!B29 -> 2925000 | F15: =F11*Parametros!D19*Parametros!B29 -> 3375000 | G15: =G11*Parametros!D19*Parametros!B29 -> 3825000 | H15: =SUM(B15:G15) -> 15300000
A16: Ingresos delivery (20% del fee) | B16: =B8*(Parametros!D21*Parametros!B34+Parametros!D22*Parametros!B35+Parametros!D23*Parametros!B36)*(1-Parametros!B33) -> 415200 | C16: =C8*(Parametros!D21*Parametros!B34+Parametros!D22*Parametros!B35+Parametros!D23*Parametros!B36)*(1-Parametros!B33) -> 830400 | D16: =D8*(Parametros!D21*Parametros!B34+Parametros!D22*Parametros!B35+Parametros!D23*Parametros!B36)*(1-Parametros!B33) -> 1141800 | E16: =E8*(Parametros!D21*Parametros!B34+Parametros!D22*Parametros!B35+Parametros!D23*Parametros!B36)*(1-Parametros!B33) -> 1349400 | F16: =F8*(Parametros!D21*Parametros!B34+Parametros!D22*Parametros!B35+Parametros!D23*Parametros!B36)*(1-Parametros!B33) -> 1557000 | G16: =G8*(Parametros!D21*Parametros!B34+Parametros!D22*Parametros!B35+Parametros!D23*Parametros!B36)*(1-Parametros!B33) -> 1764600 | H16: =SUM(B16:G16) -> 7058400
A17: Ingreso operativo 5% embebido ($) | B17: =B11*Parametros!B30 -> 1500000 | C17: =C11*Parametros!B30 -> 3000000 | D17: =D11*Parametros!B30 -> 4125000 | E17: =E11*Parametros!B30 -> 4875000 | F17: =F11*Parametros!B30 -> 5625000 | G17: =G11*Parametros!B30 -> 6375000 | H17: =SUM(B17:G17) -> 25500000
A18: Ingresos publicidad comercios ($) | B18: =B9*Parametros!B41*Parametros!B42 -> 180000 | C18: =C9*Parametros!B41*Parametros!B42 -> 330000 | D18: =D9*Parametros!B41*Parametros!B42 -> 480000 | E18: =E9*Parametros!B41*Parametros!B42 -> 600000 | F18: =F9*Parametros!B41*Parametros!B42 -> 720000 | G18: =G9*Parametros!B41*Parametros!B42 -> 825000 | H18: =SUM(B18:G18) -> 3135000
A19: TOTAL INGRESOS BRUTOS ($) | B19: =SUM(B14:B18) -> 2995200 | C19: =SUM(C14:C18) -> 9560400 | D19: =SUM(D14:D18) -> 13171800 | E19: =SUM(E14:E18) -> 15599400 | F19: =SUM(F14:F18) -> 18027000 | G19: =SUM(G14:G18) -> 20439600 | H19: =SUM(B19:G19) -> 79793400
A21: EGRESOS
A22: Costo MercadoPago ($) | B22: =B11*Parametros!B32*Parametros!B31 -> 600000 | C22: =C11*Parametros!B32*Parametros!B31 -> 1200000 | D22: =D11*Parametros!B32*Parametros!B31 -> 1650000 | E22: =E11*Parametros!B32*Parametros!B31 -> 1950000 | F22: =F11*Parametros!B32*Parametros!B31 -> 2250000 | G22: =G11*Parametros!B32*Parametros!B31 -> 2550000 | H22: =SUM(B22:G22) -> 10200000
A23: Gastos fijos mensuales ($) | B23: =Parametros!B39 -> 440641 | C23: =Parametros!B39 -> 440641 | D23: =Parametros!B39 -> 440641 | E23: =Parametros!B39 -> 440641 | F23: =Parametros!B39 -> 440641 | G23: =Parametros!B39 -> 440641 | H23: =SUM(B23:G23) -> 2643846
A24: Cashback MOOVER estimado ($) | B24: =B11*0.01 -> 300000 | C24: =C11*0.01 -> 600000 | D24: =D11*0.01 -> 825000 | E24: =E11*0.01 -> 975000 | F24: =F11*0.01 -> 1125000 | G24: =G11*0.01 -> 1275000 | H24: =SUM(B24:G24) -> 5100000
A25: Reembolsos y cancelaciones ($) | B25: =B11*0.02 -> 600000 | C25: =C11*0.02 -> 1200000 | D25: =D11*0.02 -> 1650000 | E25: =E11*0.02 -> 1950000 | F25: =F11*0.02 -> 2250000 | G25: =G11*0.02 -> 2550000 | H25: =SUM(B25:G25) -> 10200000
A26: TOTAL EGRESOS ($) | B26: =SUM(B22:B25) -> 1940641 | C26: =SUM(C22:C25) -> 3440641 | D26: =SUM(D22:D25) -> 4565641 | E26: =SUM(E22:E25) -> 5315641 | F26: =SUM(F22:F25) -> 6065641 | G26: =SUM(G22:G25) -> 6815641 | H26: =SUM(B26:G26) -> 28143846
A28: RESULTADO
A29: RESULTADO NETO MENSUAL ($) | B29: =B19-B26 -> 1054559 | C29: =C19-C26 -> 6119759 | D29: =D19-D26 -> 8606159 | E29: =E19-E26 -> 10283759 | F29: =F19-F26 -> 11961359 | G29: =G19-G26 -> 13623959 | H29: =SUM(B29:G29) -> 51649554
A30: Retiro fundador (10% si neto > 0) | B30: =IF(B29>0,B29*Parametros!B40,0) -> 105455.9 | C30: =IF(C29>0,C29*Parametros!B40,0) -> 611975.9 | D30: =IF(D29>0,D29*Parametros!B40,0) -> 860615.9 | E30: =IF(E29>0,E29*Parametros!B40,0) -> 1028375.9 | F30: =IF(F29>0,F29*Parametros!B40,0) -> 1196135.9 | G30: =IF(G29>0,G29*Parametros!B40,0) -> 1362395.9 | H30: =SUM(B30:G30) -> 5164955.4
A31: QUEDA EN CAJA ($) | B31: =B29-B30 -> 949103.1 | C31: =C29-C30 -> 5507783.1 | D31: =D29-D30 -> 7745543.1 | E31: =E29-E30 -> 9255383.1 | F31: =F29-F30 -> 10765223 | G31: =G29-G30 -> 12261563 | H31: =SUM(B31:G31) -> 46484599
A32: CAJA ACUMULADA ($) | B32: =B31 -> 949103.1 | C32: =B32+C31 -> 6456886.2 | D32: =C32+D31 -> 14202429 | E32: =D32+E31 -> 23457812 | F32: =E32+F31 -> 34223036 | G32: =F32+G31 -> 46484599
A34: METRICAS CLAVE
A35: Margen neto (%) | B35: =IF(B19=0,0,B29/B19) -> 0.352083 | C35: =IF(C19=0,0,C29/C19) -> 0.64011537 | D35: =IF(D19=0,0,D29/D19) -> 0.65337759 | E35: =IF(E19=0,0,E29/E19) -> 0.65924068 | F35: =IF(F19=0,0,F29/F19) -> 0.66352466 | G35: =IF(G19=0,0,G29/G19) -> 0.66654724
A36: Ingreso por pedido ($) | B36: =IF(B8=0,0,B19/B8) -> 2496 | C36: =IF(C8=0,0,C19/C8) -> 3983.5 | D36: =IF(D8=0,0,D19/D8) -> 3991.4545 | E36: =IF(E8=0,0,E19/E8) -> 3999.8462 | F36: =IF(F8=0,0,F19/F8) -> 4006 | G36: =IF(G8=0,0,G19/G8) -> 4007.7647
A37: GMV diario ($) | B37: =B11/30 -> 1000000 | C37: =C11/30 -> 2000000 | D37: =D11/30 -> 2750000 | E37: =E11/30 -> 3250000 | F37: =F11/30 -> 3750000 | G37: =G11/30 -> 4250000
