Workbook

Sheet Supuestos
A1: MOOVY — Simulador de crecimiento
A2: Editá SOLO las celdas azules sobre amarillo. Lo negro se calcula solo.
A4: SUPUESTOS (editables)
A5: Costo fijo mensual de Moovy | B5: 440000
A6: Ticket promedio (subtotal) | B6: 10000
A7: Envío promedio | B7: 2500
A8: Comisión comercio (mes 2+) | B8: 0.1
A9: % Moovy del envío | B9: 0.2
A10: Reserva MercadoPago | B10: 0.076
A11: Cashback puntos MOOVER | B11: 0.01
A13: CÁLCULOS (automáticos)
A14: Neto Moovy por pedido PAGO | B14: =(B6*B8+B7*B9)*(1-B10)-B6*B11 -> 1286
A15: Neto Moovy por pedido en MES GRATIS | B15: =(B7*B9)*(1-B10)-B6*B11 -> 362
A16: Punto de equilibrio (pedidos pagos/mes) | B16: =ROUND(B5/B14,0) -> 342
A18: Nota: el neto por pedido ya descuenta MercadoPago y el 1% de puntos.

Sheet Proyeccion
A1: Proyección 12 meses — cambiá los pedidos (azul) y todo recalcula
A3: Concepto | B3: Mes 1 | C3: Mes 2 | D3: Mes 3 | E3: Mes 4 | F3: Mes 5 | G3: Mes 6 | H3: Mes 7 | I3: Mes 8 | J3: Mes 9 | K3: Mes 10 | L3: Mes 11 | M3: Mes 12
A4: Pedidos de comercios PAGANDO | B4: 0 | C4: 150 | D4: 300 | E4: 440 | F4: 600 | G4: 800 | H4: 950 | I4: 1100 | J4: 1300 | K4: 1500 | L4: 1750 | M4: 2000
A5: Pedidos en MES GRATIS | B5: 100 | C5: 70 | D5: 80 | E5: 80 | F5: 100 | G5: 100 | H5: 100 | I5: 100 | J5: 100 | K5: 100 | L5: 100 | M5: 100
A6: Pedidos totales | B6: =B4+B5 -> 100 | C6: =C4+C5 -> 220 | D6: =D4+D5 -> 380 | E6: =E4+E5 -> 520 | F6: =F4+F5 -> 700 | G6: =G4+G5 -> 900 | H6: =H4+H5 -> 1050 | I6: =I4+I5 -> 1200 | ... M6: =M4+M5 -> 2100
A7: GMV (facturación bruta) | B7: =B6*Supuestos!$B$6 -> 1000000 | C7: =C6*Supuestos!$B$6 -> 2200000 | D7: =D6*Supuestos!$B$6 -> 3800000 | E7: =E6*Supuestos!$B$6 -> 5200000 | F7: =F6*Supuestos!$B$6 -> 7000000 | G7: =G6*Supuestos!$B$6 -> 9000000 | H7: =H6*Supuestos!$B$6 -> 10500000 | I7: =I6*Supuestos!$B$6 -> 12000000 | ... M7: =M6*Supuestos!$B$6 -> 21000000
A8: Ingreso Moovy | B8: =B4*Supuestos!$B$14+B5*Supuestos!$B$15 -> 36200 | C8: =C4*Supuestos!$B$14+C5*Supuestos!$B$15 -> 218240 | D8: =D4*Supuestos!$B$14+D5*Supuestos!$B$15 -> 414760 | E8: =E4*Supuestos!$B$14+E5*Supuestos!$B$15 -> 594800 | F8: =F4*Supuestos!$B$14+F5*Supuestos!$B$15 -> 807800 | G8: =G4*Supuestos!$B$14+G5*Supuestos!$B$15 -> 1065000 | H8: =H4*Supuestos!$B$14+H5*Supuestos!$B$15 -> 1257900 | I8: =I4*Supuestos!$B$14+I5*Supuestos!$B$15 -> 1450800 | ... M8: =M4*Supuestos!$B$14+M5*Supuestos!$B$15 -> 2608200
A9: Costo fijo | B9: =Supuestos!$B$5 -> 440000 | C9: =Supuestos!$B$5 -> 440000 | D9: =Supuestos!$B$5 -> 440000 | E9: =Supuestos!$B$5 -> 440000 | F9: =Supuestos!$B$5 -> 440000 | G9: =Supuestos!$B$5 -> 440000 | H9: =Supuestos!$B$5 -> 440000 | I9: =Supuestos!$B$5 -> 440000 | ... M9: =Supuestos!$B$5 -> 440000
A10: Resultado del mes | B10: =B8-B9 -> -403800 | C10: =C8-C9 -> -221760 | D10: =D8-D9 -> -25240 | E10: =E8-E9 -> 154800 | F10: =F8-F9 -> 367800 | G10: =G8-G9 -> 625000 | H10: =H8-H9 -> 817900 | I10: =I8-I9 -> 1010800 | ... M10: =M8-M9 -> 2168200
A11: Resultado ACUMULADO | B11: =B10 -> -403800 | C11: =B11+C10 -> -625560 | D11: =C11+D10 -> -650800 | E11: =D11+E10 -> -496000 | F11: =E11+F10 -> -128200 | G11: =F11+G10 -> 496800 | H11: =G11+H10 -> 1314700 | I11: =H11+I10 -> 2325500 | J11: =I11+J10 -> 3593500 | ... M11: =L11+M10 -> 9133600
A12: ¿Se paga sola? (mes en verde) | B12: =IF(B10>=0,"SI","no") -> no | C12: =IF(C10>=0,"SI","no") -> no | D12: =IF(D10>=0,"SI","no") -> no | E12: =IF(E10>=0,"SI","no") -> SI | F12: =IF(F10>=0,"SI","no") -> SI | G12: =IF(G10>=0,"SI","no") -> SI | H12: =IF(H10>=0,"SI","no") -> SI | I12: =IF(I10>=0,"SI","no") -> SI | ... M12: =IF(M10>=0,"SI","no") -> SI
A14: Referencias rápidas
A15: Break-even = pedidos pagos que cubren el costo fijo (ver Supuestos).
A16: Los pedidos (filas azules) son un supuesto conservador — se calibran con el piloto de Pixel Point.
